"touchlaunch/__init__,py"
touchlaunch/launcher.py
touchlaunch-0.0.1.dist-info/METADATA
touchlaunch-0.0.1.dist-info/WHEEL
touchlaunch-0.0.1.dist-info/RECORD
