Metadata-Version: 2.4
Name: touchlaunch
Version: 0.0.1
Summary: An automated launcher for TouchDesigner Projects.
Author-email: Wieland Hilker <Wieland@PlusPlus.One>
License-Expression: MIT
Requires-Python: >=3.11
Requires-Dist: python-dotenv>=1.1.1
